README.md
setup.py
bluelens_spawning_pool/__init__.py
bluelens_spawning_pool/spawning_pool.py
bluelens_spawning_pool.egg-info/PKG-INFO
bluelens_spawning_pool.egg-info/SOURCES.txt
bluelens_spawning_pool.egg-info/dependency_links.txt
bluelens_spawning_pool.egg-info/requires.txt
bluelens_spawning_pool.egg-info/top_level.txt