Metadata-Version: 1.0
Name: bluelens-spawning-pool
Version: 1.0.10
Summary: bluelens-spawning-pool
Home-page: UNKNOWN
Author: UNKNOWN
Author-email: master@bluehack.net
License: UNKNOWN
Keywords: bluelens-spawning-pool
Platform: UNKNOWN
